sums_learner/__init__.py
sums_learner/summation.py
sums_learner-0.4.dist-info/LICENSE
sums_learner-0.4.dist-info/WHEEL
sums_learner-0.4.dist-info/METADATA
sums_learner-0.4.dist-info/RECORD
